imagetobrailleart.py
modifiedbraillegraph.py
imagetobrailleart-0.0.6.dist-info/LICENSE.txt
imagetobrailleart-0.0.6.dist-info/METADATA
imagetobrailleart-0.0.6.dist-info/WHEEL
imagetobrailleart-0.0.6.dist-info/top_level.txt
imagetobrailleart-0.0.6.dist-info/RECORD
