Metadata-Version: 2.1
Name: imagetobrailleart
Version: 0.0.6
Summary: To convert any image or text into braille art
Home-page: https://pypi.org/project/imagetobrailleart/
Author: Yash Chauhan
Author-email: chauhanyash1029@gmail.com
License: MIT
Keywords: braille,art,openCV
Platform: UNKNOWN
Classifier: Development Status :: 5 - Production/Stable
Classifier: Intended Audience :: Education
Classifier: Operating System :: OS Independent
Classifier: License :: OSI Approved :: MIT License
Classifier: Programming Language :: Python :: 3
Requires-Dist: opencv-python (~=4.5.3.56)
Requires-Dist: Pillow (~=8.3.1)
